malayalam_asr_benchmarking/__init__.py
malayalam_asr_benchmarking/_modidx.py
malayalam_asr_benchmarking/commonvoice.py
malayalam_asr_benchmarking/msc.py
malayalam_asr_benchmarking/utils.py
malayalam_asr_benchmarking-0.0.4.dist-info/LICENSE
malayalam_asr_benchmarking-0.0.4.dist-info/METADATA
malayalam_asr_benchmarking-0.0.4.dist-info/WHEEL
malayalam_asr_benchmarking-0.0.4.dist-info/entry_points.txt
malayalam_asr_benchmarking-0.0.4.dist-info/top_level.txt
malayalam_asr_benchmarking-0.0.4.dist-info/RECORD
