Metadata-Version: 2.1
Name: malayalam_asr_benchmarking
Version: 0.0.4
Summary: A study to benchmark whisper based ASRs in Malayalam
Home-page: https://github.com/kurianbenoy/malayalam_asr_benchmarking
Author: kurianbenoy
Author-email: kurian.bkk@gmail.com
License: MIT License
Keywords: nbdev jupyter notebook python
Classifier: Development Status :: 4 - Beta
Classifier: Intended Audience :: Developers
Classifier: Natural Language :: English
Classifier: Programming Language :: Python :: 3.7
Classifier: Programming Language :: Python :: 3.8
Classifier: Programming Language :: Python :: 3.9
Classifier: Programming Language :: Python :: 3.10
Classifier: License :: OSI Approved :: MIT License
Requires-Python: >=3.7
License-File: LICENSE
Requires-Dist: transformers <5,>=4.0.0
Requires-Dist: datasets
Requires-Dist: jiwer
Requires-Dist: numerize
Requires-Dist: pandas
Requires-Dist: librosa
Requires-Dist: soundfile ==0.12.1
Requires-Dist: whisper-normalizer
Requires-Dist: faster-whisper
Requires-Dist: torch >=1.7
Provides-Extra: dev
Requires-Dist: nbdev ; extra == 'dev'
Requires-Dist: black ; extra == 'dev'
